setup.py
exon/__init__.py
exon/http/__init__.py
exon/testing/__init__.py
exon/unittest/FileTest.py
exon/unittest/FilesystemTest.py
exon/unittest/LvmTest.py
exon/unittest/MdadmTest.py
exon/unittest/NetworkTest.py
exon/unittest/RunTest.py
exon/unittest/ShareTest.py
exon/unittest/SystemDTest.py
exon/unittest/UserTest.py
exon/unittest/__init__.py
exon/utils/__init__.py
exon/utils/fileutils.py
exon/utils/arch/__init__.py
exon/utils/arch/netctl.py
exon/utils/command/__init__.py
exon/utils/command/execute.py
exon/utils/disk/__init__.py
exon/utils/disk/filesystem.py
exon/utils/disk/lvm.py
exon/utils/disk/mdadm.py
exon/utils/disk/part.py
exon/utils/ldap/__init__.py
exon/utils/ldap/parseRecord.py
exon/utils/ldap/samba.py
exon/utils/samba/__init__.py
exon/utils/samba/usersandgroup.py
exon/utils/share/AfpShare.py
exon/utils/share/NfsShare.py
exon/utils/share/ShareManager.py
exon/utils/share/SmbShare.py
exon/utils/share/__init__.py
exon/utils/systemd/__init__.py
exon/utils/systemd/services.py
exon/utils/systemd/units.py
exon_python_libs.egg-info/PKG-INFO
exon_python_libs.egg-info/SOURCES.txt
exon_python_libs.egg-info/dependency_links.txt
exon_python_libs.egg-info/requires.txt
exon_python_libs.egg-info/top_level.txt