Metadata-Version: 1.0
Name: exon-python-libs
Version: 0.1.2
Summary: Exon Python Library
Home-page: http://exon.conrad.pics
Author: Stephan Conrad
Author-email: stephan@conrad.pics
License: Apache License (2.0)
Keywords: exon-python-libs
Platform: UNKNOWN
